vemmio/__init__.py
vemmio/capability.py
vemmio/device.py
vemmio/device_factory.py
vemmio/exceptions.py
vemmio/flood.py
vemmio/implant.py
vemmio/motion.py
vemmio/vemmio.py
vemmio/api/__init__.py
vemmio/api/vemmioApiInterface.py
vemmio/api/vemmioHttpRestApi.py
vemmio/api/vemmioWebsocketApi.py
vemmio/models/__init__.py
vemmio/models/base_model.py
vemmio/models/device_info_model.py
vemmio/models/flood_detector_status_model.py
vemmio/models/implant_status_model.py
vemmio/models/motion_detector_status_model.py
vemmio-0.1.1.dist-info/licenses/LICENSE.txt
vemmio-0.1.1.dist-info/METADATA
vemmio-0.1.1.dist-info/WHEEL
vemmio-0.1.1.dist-info/top_level.txt
vemmio-0.1.1.dist-info/RECORD
