Metadata-Version: 2.4
Name: vemmio
Version: 0.1.1
Summary: Vemmio Python Client
Author-email: Mateusz Mamala <m.mamala@vemmio.com>
License-Expression: Apache-2.0
Classifier: Programming Language :: Python :: 3
Classifier: Operating System :: OS Independent
Requires-Python: >=3.13
License-File: LICENSE.txt
Dynamic: license-file
